setup.cfg
setup.py
./.gitignore
./CHANGES.md
./LICENSE
./README.es.md
./README.md
./setup.cfg
./setup.py
./dist/modeltranslation-0.2-py2-none-any.whl
./dist/modeltranslation-0.2.tar.gz
./dist/modeltranslation-0.21.tar.gz
./dist/modeltranslation-0.22.tar.gz
./dist/modeltranslation-0.23.tar.gz
./modeltranslation.egg-info/PKG-INFO
./modeltranslation.egg-info/SOURCES.txt
./modeltranslation.egg-info/dependency_links.txt
./modeltranslation.egg-info/requires.txt
./modeltranslation.egg-info/top_level.txt
./modeltranslation/static/css/modeltranslation/import.css
./modeltranslation/static/css/modeltranslation/search.css
./modeltranslation/static/css/modeltranslation/forms/common.css
./modeltranslation/static/js/modeltranslation/import.js
./modeltranslation/static/js/modeltranslation/forms/common.js
./modeltranslation/templates/admin/modeltranslation/app_index.html
./modeltranslation/templates/modeltranslation/admin/admin.html
./modeltranslation/templates/modeltranslation/admin/edit_translation.html
./modeltranslation/templates/modeltranslation/admin/export_translations.po
./modeltranslation/templates/modeltranslation/admin/form_fieldset_bootstrap_render.html
./modeltranslation/templates/modeltranslation/admin/list.html
./modeltranslation/templates/modeltranslation/admin/search.html
./modeltranslation/templates/modeltranslation/admin/update_translations_ok.html
modeltranslation/__init__.py
modeltranslation/decorators.py
modeltranslation/forms.py
modeltranslation/models.py
modeltranslation/tests.py
modeltranslation/transcache.py
modeltranslation/translation.py
modeltranslation/urls.py
modeltranslation/views.py
modeltranslation.egg-info/PKG-INFO
modeltranslation.egg-info/SOURCES.txt
modeltranslation.egg-info/dependency_links.txt
modeltranslation.egg-info/requires.txt
modeltranslation.egg-info/top_level.txt
modeltranslation/admin/__init__.py
modeltranslation/admin/forms.py
modeltranslation/admin/views.py
modeltranslation/migrations/0001_initial.py
modeltranslation/migrations/0002_auto_20151109_1453.py
modeltranslation/migrations/0003_auto_20151211_1232.py
modeltranslation/migrations/0004_auto_20151211_1235.py
modeltranslation/migrations/0005_auto_20160107_1058.py
modeltranslation/migrations/0006_auto_20160119_1321.py
modeltranslation/migrations/0007_auto_20160119_1351.py
modeltranslation/migrations/0008_auto_20160119_1425.py
modeltranslation/migrations/__init__.py
