Metadata-Version: 1.1
Name: modeltranslation
Version: 0.24
Summary: Modeltranslation is an utility to translate Django model fields.
Home-page: https://github.com/intelligenia/modeltranslation
Author: intelligenia S.L.
Author-email: diego@intelligenia.es
License: MIT
Keywords: modeltranslation translations
Platform: UNKNOWN
Classifier: Development Status :: 5 - Production/Stable
Classifier: Framework :: Django
Classifier: License :: OSI Approved :: MIT License
